pytools/dotenv.py
team_qa_tools_python-0.1.0.dist-info/METADATA
team_qa_tools_python-0.1.0.dist-info/WHEEL
team_qa_tools_python-0.1.0.dist-info/top_level.txt
team_qa_tools_python-0.1.0.dist-info/RECORD
