Metadata-Version: 2.4
Name: team-qa-tools-python
Version: 0.1.0
Summary: python工具集
Requires-Python: >=3.13
Requires-Dist: python-dotenv>=1.1.1
